auto_app/__init__.py
auto_app/auto_app.py
auto_app/cli_auto_app.py
auto_app/streamlit_demo.py
auto_route/__init__.py
auto_route/auto_route.py
auto_route/create_composed_class.py
auto_route/generator.py
auto_route-0.1.7.dist-info/LICENSE
auto_route-0.1.7.dist-info/METADATA
auto_route-0.1.7.dist-info/WHEEL
auto_route-0.1.7.dist-info/top_level.txt
auto_route-0.1.7.dist-info/RECORD
