Metadata-Version: 2.1
Name: auto-route
Version: 0.1.7
Summary: Thank you for your interest in contributing to the AutoRoute project! Our goal is to simplify and automate the creation of SaaS/PaaS solutions. We're excited to welcome you to our community.
Home-page: https://github.com/Bucanero06/auto_route
Author: Ruben Fernandez
Author-email: ruben@carbonyl.org
License-File: LICENSE
Requires-Dist: fastapi
Requires-Dist: pydantic
Requires-Dist: uvicorn
